{
  "kind": "singleType",
  "collectionName": "pre_headers",
  "info": {
    "singularName": "pre-header",
    "pluralName": "pre-headers",
    "displayName": "PreHeader",
    "description": ""
  },
  "options": {
    "draftAndPublish": false
  },
  "pluginOptions": {
    "i18n": {
      "localized": true
    }
  },
  "attributes": {
    "leftCtas": {
      "type": "component",
      "repeatable": true,
      "component": "components.pre-header-button",
      "required": true,
      "min": 1,
      "pluginOptions": {
        "i18n": {
          "localized": true
        }
      }
    },
    "rightCtas": {
      "type": "component",
      "repeatable": true,
      "component": "components.pre-header-button",
      "required": true,
      "min": 1,
      "pluginOptions": {
        "i18n": {
          "localized": true
        }
      }
    }
  }
}
